<?xml version="1.0"?>
<!DOCTYPE hibernate-mapping PUBLIC "-//Hibernate/Hibernate Mapping DTD 3.0//EN"
"http://www.hibernate.org/dtd/hibernate-mapping-3.0.dtd">
<!-- Generated May 26, 2016 9:42:29 AM by Hibernate Tools 4.3.1.Final -->
<hibernate-mapping>
	<class name="org.cgiar.ccafs.marlo.data.model.CrpProgram" table="crp_programs"
		optimistic-lock="version">
		<id name="id" type="java.lang.Long">
			<column name="id" />
			<generator class="identity" />
		</id>
		<many-to-one name="crp" class="org.cgiar.ccafs.marlo.data.model.Crp"
			fetch="select">
			<column name="crp_id" not-null="true" />
		</many-to-one>
		<property name="name" type="string">
			<column name="name" length="65535" not-null="true" />
		</property>
		<property name="color" type="string">
			<column name="color" length="8" />
		</property>
		<property name="acronym" type="string">
			<column name="acronym" length="50" not-null="true" />
		</property>
		<property name="programType" type="int">
			<column name="program_type" not-null="true" />
		</property>
		 <property name="baseLine"  type="java.lang.Boolean">
            <column name="base_line"  default="0"/>
        </property>
		<set lazy="true" name="crpClusterOfActivities" order-by="id"
			table="crp_cluster_of_activities" inverse="true" fetch="select">
			<key>
				<column name="crp_program_id" not-null="true" />
			</key>
			<one-to-many class="org.cgiar.ccafs.marlo.data.model.CrpClusterOfActivity" />
		</set>
		<set lazy="true" name="crpProgramLeaders" table="crp_program_leaders"
			inverse="true" fetch="select" order-by="id">
			<key>
				<column name="crp_program_id" not-null="true" />
			</key>
			<one-to-many class="org.cgiar.ccafs.marlo.data.model.CrpProgramLeader" />
		</set>
		<set lazy="true" name="crpProgramOutcomes" order-by="id"
			table="crp_program_outcomes" inverse="true" fetch="select">
			<key>
				<column name="crp_program_id" not-null="true" />
			</key>
			<one-to-many class="org.cgiar.ccafs.marlo.data.model.CrpProgramOutcome" />
		</set>
		<set name="crpProgramCountries" table="crp_program_countries"
			order-by="id" inverse="true" lazy="true" fetch="select">
			<key>
				<column name="program_id" not-null="true" />
			</key>
			<one-to-many class="org.cgiar.ccafs.marlo.data.model.CrpProgramCountry" />
		</set>
		<property name="active" type="boolean">
			<column name="is_active" not-null="true" />
		</property>
		<property name="modificationJustification" type="string">
			<column name="modification_justification" length="65535"
				not-null="true" />
		</property>
		<property name="activeSince" type="timestamp">
			<column name="active_since" length="19" not-null="true" />
		</property>
		<many-to-one name="createdBy" class="org.cgiar.ccafs.marlo.data.model.User"
			fetch="select">
			<column name="created_by" not-null="false" />
		</many-to-one>
		<many-to-one name="modifiedBy" class="org.cgiar.ccafs.marlo.data.model.User"
			fetch="select">
			<column name="modified_by" not-null="true" />
		</many-to-one>

		<set name="sectionStatuses" table="section_statuses" order-by="id"
			inverse="true" lazy="true" fetch="select">
			<key>
				<column name="crp_program_id" />
			</key>
			<one-to-many class="org.cgiar.ccafs.marlo.data.model.SectionStatus" />
		</set>

		<set name="submissions" order-by="id" table="submissions" inverse="true"
			lazy="true" fetch="select">
			<key>
				<column name="crp_program_id" not-null="true" />
			</key>
			<one-to-many class="org.cgiar.ccafs.marlo.data.model.Submission" />
		</set>

		<set name="liaisonInstitutions" table="liaison_institutions"
			inverse="true" lazy="true" fetch="select">
			<key>
				<column name="crp_program" />
			</key>
			<one-to-many class="org.cgiar.ccafs.marlo.data.model.LiaisonInstitution" />
		</set>
		<set name="projectFocuses" table="project_focuses" inverse="true"
			lazy="true" fetch="select">
			<key>
				<column name="program_id" not-null="true" />
			</key>
			<one-to-many class="org.cgiar.ccafs.marlo.data.model.ProjectFocus" />
		</set>
	</class>
</hibernate-mapping>
